lifx/__init__.py
lifx/msg.py
lifx/lan/__init__.py
lifx/lan/discovery.py
lifx/lan/header.py
lifx/lan/light.py
lifx/lan/msg.py
lifx/lan/client/__init__.py
lifx/lan/client/asynchronous.py
lifx/tests/__init__.py
lifx/tests/test_doctests.py
lifx_lib-0.9.1.dist-info/LICENSE
lifx_lib-0.9.1.dist-info/METADATA
lifx_lib-0.9.1.dist-info/WHEEL
lifx_lib-0.9.1.dist-info/top_level.txt
lifx_lib-0.9.1.dist-info/RECORD
