Metadata-Version: 2.1
Name: lifx-lib
Version: 0.9.1
Summary: A python3 library able to encode/decode Lifx (lan) messages
Home-page: https://github.com/majamassarini/lifx-lib
Author: Maja Massarini
Author-email: maja.massarini@gmail.com
License: MIT
Platform: UNKNOWN
Classifier: Development Status :: 3 - Alpha
Classifier: License :: OSI Approved :: MIT License
Classifier: Operating System :: POSIX :: Linux
Classifier: Programming Language :: Python :: 3.8
Classifier: Topic :: Communications
Classifier: Intended Audience :: Developers
License-File: LICENSE
